elevenfiftynine_python_core_lib/__init__.py
elevenfiftynine_python_core_lib/foo.py
elevenfiftynine_python_core_lib-0.1.0.dist-info/LICENSE
elevenfiftynine_python_core_lib-0.1.0.dist-info/METADATA
elevenfiftynine_python_core_lib-0.1.0.dist-info/WHEEL
elevenfiftynine_python_core_lib-0.1.0.dist-info/RECORD
