Metadata-Version: 2.1
Name: elevenfiftynine_python_core_lib
Version: 0.1.0
Summary: This is a template repository for Python projects that use Poetry for their dependency management.
Home-page: https://github.com/fpgmaas/elevenfiftynine-python-core-lib
Author: Florian Maas
Author-email: ffpgmaas@gmail.com
Requires-Python: >=3.8,<4.0
Classifier: Programming Language :: Python :: 3
Classifier: Programming Language :: Python :: 3.8
Classifier: Programming Language :: Python :: 3.9
Classifier: Programming Language :: Python :: 3.10
Classifier: Programming Language :: Python :: 3.11
Classifier: Programming Language :: Python :: 3.12
Project-URL: Documentation, https://fpgmaas.github.io/elevenfiftynine-python-core-lib/
Project-URL: Repository, https://github.com/fpgmaas/elevenfiftynine-python-core-lib
